run/__init__.py
run/main.py
delphai_run_azure_container-0.0.5.dist-info/LICENCE
delphai_run_azure_container-0.0.5.dist-info/METADATA
delphai_run_azure_container-0.0.5.dist-info/WHEEL
delphai_run_azure_container-0.0.5.dist-info/top_level.txt
delphai_run_azure_container-0.0.5.dist-info/RECORD
