Metadata-Version: 2.1
Name: delphai-run-azure-container
Version: 0.0.5
Summary: A Python package to run container instance on Azure.
Home-page: https://github.com/delphai/delphai-run-container
Author: Delphai
Author-email: ahmed.mahmoud@delphai.com
License: MIT
Platform: UNKNOWN
Classifier: License :: OSI Approved :: MIT License
Classifier: Programming Language :: Python :: 3
Requires-Dist: azure-common (==1.1.15)
Requires-Dist: azure-mgmt-resource (>=1.1.0)
Requires-Dist: azure-mgmt-containerinstance (==1.1.0)
